whale_revenue_projection/.DS_Store
whale_revenue_projection/__init__.py
whale_revenue_projection/get_ltv.py
whale_revenue_projection/get_survival.py
whale_revenue_projection/revenue_prediction.py
whale_revenue_projection/validation_prediction.py
whale_revenue_projection-0.0.2.dist-info/WHEEL
whale_revenue_projection-0.0.2.dist-info/METADATA
whale_revenue_projection-0.0.2.dist-info/RECORD
